{
  "colors": [
    {
      "image": "/yarns/sandnes-garn-mandarin-petit/images/1001.jpg",
      "name": "1001",
      "color": "rgb(225,225,228)",
      "yarn": "sandnes-garn-mandarin-petit"
    },
    {
      "image": "/yarns/sandnes-garn-mandarin-petit/images/1002.jpg",
      "name": "1002",
      "color": "rgb(220,219,212)",
      "yarn": "sandnes-garn-mandarin-petit"
    },
    {
      "image": "/yarns/sandnes-garn-mandarin-petit/images/1012.jpg",
      "name": "1012",
      "color": "rgb(219,206,186)",
      "yarn": "sandnes-garn-mandarin-petit"
    },
    {
      "image": "/yarns/sandnes-garn-mandarin-petit/images/1099.jpg",
      "name": "1099",
      "color": "rgb(4,3,5)",
      "yarn": "sandnes-garn-mandarin-petit"
    },
    {
      "image": "/yarns/sandnes-garn-mandarin-petit/images/2102.jpg",
      "name": "2102",
      "color": "rgb(220,194,114)",
      "yarn": "sandnes-garn-mandarin-petit"
    },
    {
      "image": "/yarns/sandnes-garn-mandarin-petit/images/2205.jpg",
      "name": "2205",
      "color": "rgb(178,170,154)",
      "yarn": "sandnes-garn-mandarin-petit"
    },
    {
      "image": "/yarns/sandnes-garn-mandarin-petit/images/3009.jpg",
      "name": "3009",
      "color": "rgb(235,118,64)",
      "yarn": "sandnes-garn-mandarin-petit"
    },
    {
      "image": "/yarns/sandnes-garn-mandarin-petit/images/3011.jpg",
      "name": "3011",
      "color": "rgb(194,181,157)",
      "yarn": "sandnes-garn-mandarin-petit"
    },
    {
      "image": "/yarns/sandnes-garn-mandarin-petit/images/3051.jpg",
      "name": "3051",
      "color": "rgb(146,116,104)",
      "yarn": "sandnes-garn-mandarin-petit"
    },
    {
      "image": "/yarns/sandnes-garn-mandarin-petit/images/3528.jpg",
      "name": "3528",
      "color": "rgb(208,99,86)",
      "yarn": "sandnes-garn-mandarin-petit"
    },
    {
      "image": "/yarns/sandnes-garn-mandarin-petit/images/3535.jpg",
      "name": "3535",
      "color": "rgb(181,108,95)",
      "yarn": "sandnes-garn-mandarin-petit"
    },
    {
      "image": "/yarns/sandnes-garn-mandarin-petit/images/3870.jpg",
      "name": "3870",
      "color": "rgb(131,117,110)",
      "yarn": "sandnes-garn-mandarin-petit"
    },
    {
      "image": "/yarns/sandnes-garn-mandarin-petit/images/4002.jpg",
      "name": "4002",
      "color": "rgb(212,169,162)",
      "yarn": "sandnes-garn-mandarin-petit"
    },
    {
      "image": "/yarns/sandnes-garn-mandarin-petit/images/4018.jpg",
      "name": "4018",
      "color": "rgb(199,56,47)",
      "yarn": "sandnes-garn-mandarin-petit"
    },
    {
      "image": "/yarns/sandnes-garn-mandarin-petit/images/4213.jpg",
      "name": "4213",
      "color": "rgb(228,168,169)",
      "yarn": "sandnes-garn-mandarin-petit"
    },
    {
      "image": "/yarns/sandnes-garn-mandarin-petit/images/4315.jpg",
      "name": "4315",
      "color": "rgb(230,101,134)",
      "yarn": "sandnes-garn-mandarin-petit"
    },
    {
      "image": "/yarns/sandnes-garn-mandarin-petit/images/4323.jpg",
      "name": "4323",
      "color": "rgb(183,108,118)",
      "yarn": "sandnes-garn-mandarin-petit"
    },
    {
      "image": "/yarns/sandnes-garn-mandarin-petit/images/4335.jpg",
      "name": "4335",
      "color": "rgb(164,50,70)",
      "yarn": "sandnes-garn-mandarin-petit"
    },
    {
      "image": "/yarns/sandnes-garn-mandarin-petit/images/4418.jpg",
      "name": "4418",
      "color": "rgb(167,15,37)",
      "yarn": "sandnes-garn-mandarin-petit"
    },
    {
      "image": "/yarns/sandnes-garn-mandarin-petit/images/4626.jpg",
      "name": "4626",
      "color": "rgb(201,120,161)",
      "yarn": "sandnes-garn-mandarin-petit"
    },
    {
      "image": "/yarns/sandnes-garn-mandarin-petit/images/4813.jpg",
      "name": "4813",
      "color": "rgb(231,168,191)",
      "yarn": "sandnes-garn-mandarin-petit"
    },
    {
      "image": "/yarns/sandnes-garn-mandarin-petit/images/5023.jpg",
      "name": "5023",
      "color": "rgb(205,169,202)",
      "yarn": "sandnes-garn-mandarin-petit"
    },
    {
      "image": "/yarns/sandnes-garn-mandarin-petit/images/5252.jpg",
      "name": "5252",
      "color": "rgb(122,120,147)",
      "yarn": "sandnes-garn-mandarin-petit"
    },
    {
      "image": "/yarns/sandnes-garn-mandarin-petit/images/5844.jpg",
      "name": "5844",
      "color": "rgb(46,58,115)",
      "yarn": "sandnes-garn-mandarin-petit"
    },
    {
      "image": "/yarns/sandnes-garn-mandarin-petit/images/5930.jpg",
      "name": "5930",
      "color": "rgb(152,179,195)",
      "yarn": "sandnes-garn-mandarin-petit"
    },
    {
      "image": "/yarns/sandnes-garn-mandarin-petit/images/6015.jpg",
      "name": "6015",
      "color": "rgb(86,127,182)",
      "yarn": "sandnes-garn-mandarin-petit"
    },
    {
      "image": "/yarns/sandnes-garn-mandarin-petit/images/6032.jpg",
      "name": "6032",
      "color": "rgb(122,137,156)",
      "yarn": "sandnes-garn-mandarin-petit"
    },
    {
      "image": "/yarns/sandnes-garn-mandarin-petit/images/6061.jpg",
      "name": "6061",
      "color": "rgb(47,47,59)",
      "yarn": "sandnes-garn-mandarin-petit"
    },
    {
      "image": "/yarns/sandnes-garn-mandarin-petit/images/6073.jpg",
      "name": "6073",
      "color": "rgb(2,5,25)",
      "yarn": "sandnes-garn-mandarin-petit"
    },
    {
      "image": "/yarns/sandnes-garn-mandarin-petit/images/6315.jpg",
      "name": "6315",
      "color": "rgb(69,170,199)",
      "yarn": "sandnes-garn-mandarin-petit"
    },
    {
      "image": "/yarns/sandnes-garn-mandarin-petit/images/7213.jpg",
      "name": "7213",
      "color": "rgb(145,202,197)",
      "yarn": "sandnes-garn-mandarin-petit"
    },
    {
      "image": "/yarns/sandnes-garn-mandarin-petit/images/7720.jpg",
      "name": "7720",
      "color": "rgb(155,179,173)",
      "yarn": "sandnes-garn-mandarin-petit"
    },
    {
      "image": "/yarns/sandnes-garn-mandarin-petit/images/8236.jpg",
      "name": "8236",
      "color": "rgb(90,146,93)",
      "yarn": "sandnes-garn-mandarin-petit"
    },
    {
      "image": "/yarns/sandnes-garn-mandarin-petit/images/8734.jpg",
      "name": "8734",
      "color": "rgb(128,145,83)",
      "yarn": "sandnes-garn-mandarin-petit"
    },
    {
      "image": "/yarns/sandnes-garn-mandarin-petit/images/9004.jpg",
      "name": "9004",
      "color": "rgb(230,204,113)",
      "yarn": "sandnes-garn-mandarin-petit"
    },
    {
      "image": "/yarns/sandnes-garn-mandarin-petit/images/9041.jpeg",
      "name": "9041",
      "color": "rgb(160,172,149)",
      "yarn": "sandnes-garn-mandarin-petit"
    },
    {
      "image": "/yarns/sandnes-garn-mandarin-petit/images/9463.jpg",
      "name": "9463",
      "color": "rgb(91,116,143)",
      "yarn": "sandnes-garn-mandarin-petit"
    },
    {
      "image": "/yarns/sandnes-garn-mandarin-petit/images/9825.jpg",
      "name": "9825",
      "color": "rgb(180,175,94)",
      "yarn": "sandnes-garn-mandarin-petit"
    }
  ]
}
